[
  {
    "BaseName": "Base2",
    "ExtrudeName": "Extrude_1_2",
    "StationStart": 85,
    "StationEnd": 145,
    "WallNumber": 1,
    "Cabinets": [
      {
        "SketchName": "Sketch_Cabinet1_1",
        "Height": 200,
        "Depth": 60,
        "Width": 60,
        "HasDrawers": false,
        "DistanceX": 85,
        "DistanceY": 15,
        "Drawers": {
          "SketchName": "Drawers1_1",
          "Width1": 196,
          "DistanceY1": 2,
          "Width2": 0,
          "DistanceY2": 0,
          "Width3": 0,
          "DistanceY3": 0,
          "Width4": 0,
          "DistanceY4": 0,
          "Width5": 0,
          "DistanceY5": 0
        }
      }
    ],
    "HasCountertop": false,
    "SketchName": "1_2"
  },
  {
    "BaseName": "Base2",
    "ExtrudeName": "Extrude_1_2",
    "StationStart": 145,
    "StationEnd": 400,
    "WallNumber": 1,
    "Cabinets": [
      {
        "SketchName": "Sketch_Cabinet1_2",
        "Height": 66,
        "Depth": 60,
        "Width": 50,
        "HasDrawers": false,
        "DistanceX": 145,
        "DistanceY": 70,
        "Drawers": {
          "SketchName": "Drawers1_2",
          "Width1": 62,
          "DistanceY1": 2,
          "Width2": 0,
          "DistanceY2": 0,
          "Width3": 0,
          "DistanceY3": 0,
          "Width4": 0,
          "DistanceY4": 0,
          "Width5": 0,
          "DistanceY5": 0
        }
      },
      {
        "SketchName": "Sketch_Cabinet1_3",
        "Height": 66,
        "Depth": 60,
        "Width": 50,
        "HasDrawers": false,
        "DistanceX": 195,
        "DistanceY": 70,
        "Drawers": {
          "SketchName": "Drawers1_3",
          "Width1": 62,
          "DistanceY1": 2,
          "Width2": 0,
          "DistanceY2": 0,
          "Width3": 0,
          "DistanceY3": 0,
          "Width4": 0,
          "DistanceY4": 0,
          "Width5": 0,
          "DistanceY5": 0
        }
      },
      {
        "SketchName": "Sketch_Cabinet1_4",
        "Height": 70,
        "Depth": 60,
        "Width": 55,
        "HasDrawers": true,
        "DistanceX": 245,
        "DistanceY": 70,
        "Drawers": {
          "SketchName": "Drawers1_4",
          "Width1": 15,
          "DistanceY1": 53,
          "Width2": 15,
          "DistanceY2": 36,
          "Width3": 15,
          "DistanceY3": 19,
          "Width4": 15,
          "DistanceY4": 2,
          "Width5": 0,
          "DistanceY5": 0
        }
      },
      {
        "SketchName": "Sketch_Cabinet1_5",
        "Height": 70,
        "Depth": 60,
        "Width": 50,
        "HasDrawers": false,
        "DistanceX": 300,
        "DistanceY": 70,
        "Drawers": {
          "SketchName": "Drawers1_5",
          "Width1": 66,
          "DistanceY1": 2,
          "Width2": 0,
          "DistanceY2": 0,
          "Width3": 0,
          "DistanceY3": 0,
          "Width4": 0,
          "DistanceY4": 0,
          "Width5": 0,
          "DistanceY5": 0
        }
      },
      {
        "SketchName": "Sketch_Cabinet1_6",
        "Height": 70,
        "Depth": 60,
        "Width": 50,
        "HasDrawers": false,
        "DistanceX": 350,
        "DistanceY": 70,
        "Drawers": {
          "SketchName": "Drawers1_6",
          "Width1": 66,
          "DistanceY1": 2,
          "Width2": 0,
          "DistanceY2": 0,
          "Width3": 0,
          "DistanceY3": 0,
          "Width4": 0,
          "DistanceY4": 0,
          "Width5": 0,
          "DistanceY5": 0
        }
      }
    ],
    "HasCountertop": true,
    "SketchName": "1_2"
  },
  {
    "BaseName": "Base1",
    "ExtrudeName": "Extrude_2_1",
    "StationStart": 60,
    "StationEnd": 300,
    "WallNumber": 2,
    "Cabinets": [],
    "HasCountertop": true,
    "SketchName": "2_1"
  },
  {
    "BaseName": "Base1",
    "ExtrudeName": "Extrude_3_1",
    "StationStart": 60,
    "StationEnd": 180,
    "WallNumber": 3,
    "Cabinets": [],
    "HasCountertop": true,
    "SketchName": "3_1"
  }
]